setup.cfg
setup.py
cyanite_utils/Config.py
cyanite_utils/CyaniteCassandra.py
cyanite_utils/CyaniteMetrics.py
cyanite_utils/CyanitePaths.py
cyanite_utils/__init__.py
cyanite_utils/cli.py
cyanite_utils/util.py
cyanite_utils.egg-info/PKG-INFO
cyanite_utils.egg-info/SOURCES.txt
cyanite_utils.egg-info/dependency_links.txt
cyanite_utils.egg-info/entry_points.txt
cyanite_utils.egg-info/requires.txt
cyanite_utils.egg-info/top_level.txt