Metadata-Version: 1.1
Name: cyanite-utils
Version: 0.0.12
Summary: Cyanite Utils
Home-page: https://github.com/WrathOfChris/cyanite-utils
Author: Chris Maxwell
Author-email: chris@wrathofchris.com
License: Apache
Download-URL: https://github.com/WrathOfChris/cyanite-utils/tarball/0.0.12
Platform: UNKNOWN
